telegram_logger/__init__.py
telegram_logger/exceptions.py
telegram_logger/telelog.py
telelogger-0.1.0.dist-info/METADATA
telelogger-0.1.0.dist-info/WHEEL
telelogger-0.1.0.dist-info/top_level.txt
telelogger-0.1.0.dist-info/RECORD
