Metadata-Version: 2.4
Name: telelogger
Version: 0.1.0
Summary: Python библиотека для отправки логов в Telegram через бота
Author-email: Mathew_pandora <mathew.trofimov@yandex.ru>
License-Expression: MIT
Project-URL: Homepage, https://github.com/yourusername/telegram-logger
Project-URL: Documentation, https://github.com/yourusername/telegram-logger#readme
Project-URL: Repository, https://github.com/yourusername/telegram-logger
Project-URL: Issues, https://github.com/yourusername/telegram-logger/issues
Keywords: telegram,logging,bot,logger,telegram-bot
Classifier: Development Status :: 4 - Beta
Classifier: Intended Audience :: Developers
Classifier: Programming Language :: Python :: 3
Classifier: Programming Language :: Python :: 3.7
Classifier: Programming Language :: Python :: 3.8
Classifier: Programming Language :: Python :: 3.9
Classifier: Programming Language :: Python :: 3.10
Classifier: Programming Language :: Python :: 3.11
Classifier: Programming Language :: Python :: 3.12
Classifier: Topic :: Software Development :: Libraries :: Python Modules
Classifier: Topic :: System :: Logging
Requires-Python: >=3.7
Requires-Dist: requests>=2.25.0
